Workbook

Sheet ★企业变量表
A1: ★ 企业变量表 —— 一次采集,所有文档复用
A2: 所有 T/P 类文档要填的空,其实是同一批变量。填完这张表,文档生成就从「创作」降级成「填空」—— 这是把几十份文件工作量压到接近零的关键。
A4: 变量代号 | B4: 变量名称 | C4: 采集值 | D4: 说明 / 采集要点 | E4: 用于哪些文档
A5: 一、主体信息(所有文档抬头都要用)
A6: {公司全称} | B6: 公司全称 | D6: 营业执照全称,一字不差 | E6: 全部文档
A7: {统一社会信用代码} | B7: 统一社会信用代码 | E7: 合同、协议、备案文件
A8: {法定代表人} | B8: 法定代表人 | E8: 合同、制度发文、决议
A9: {注册地址} | B9: 注册地址 | E9: 合同、送达条款
A10: {实际经营地址} | B10: 实际经营地址 | D10: 与注册地不同时须分别写明 | E10: 合同工作地点条款
A11: {其他主体} | B11: 其他关联主体 | D11: ★ 有几家?名称?关系?→ 关联主表 #9 用工主体一致性 | E11: 关联用工协议、主体确认表
A12: {签约主体} | B12: 实际签约主体 | D12: ★ 招 / 签 / 发薪 / 参保 四者是否同一主体?不一致须标出 | E12: 劳动合同、参保文件
A13: {联系人} | B13: HR对接人 / 职务 / 电话 | E13: 交付与培训安排
A14: 二、参保与地方口径(★ 一家一采,不可套模板)
A15: {参保地} | B15: 社保参保地(统筹区) | D15: 以实际参保地为准,不是注册地 | E15: 社保方案、参保文件
A16: {公积金地} | B16: 公积金统筹区 | D16: 可能与社保统筹区不一致 | E16: 公积金方案
A17: {社保基数下限} | B17: 社保缴费基数下限 | D17: ★ 元/月。不得低于此下限 | E17: 基数测算、成本测算
A18: {社保基数上限} | B18: 社保缴费基数上限 | D18: 元/月 | E18: 基数测算
A19: {公积金基数下限} | B19: 公积金缴费基数下限 | D19: ★★ 元/月。多地=当地最低工资,与社保下限【独立适用】,不得混用 | E19: 公积金方案、成本测算
A20: {最低工资} | B20: 当地最低工资标准 | D20: 元/月 | E20: 薪酬制度、试用期工资、待岗工资
A21: {单位社保比例} | B21: 单位社保合计比例 | D21: %(养老+医疗+失业+工伤) | E21: 成本测算
A22: {公积金比例} | B22: 公积金当前单位比例 | D22: %,未开缴填 0。5%–12% 区间是重要缓冲工具 | E22: 公积金过渡方案
A23: 三、用工与工时
A24: {总人数} | B24: 在册总人数 | E24: 制度、方案、成本测算
A25: {工时制度} | B25: 执行的工时制度 | D25: 标准工时 / 综合计算 / 不定时(是否已审批?) | E25: 考勤制度、加班规则、劳动合同
A26: {考勤周期} | B26: 考勤周期 | D26: 如:每月1日–月末 / 26日–25日 | E26: 考勤制度、工资条
A27: {加班审批人} | B27: 加班审批权限 | D27: 谁审批?几级? | E27: 加班审批表、考勤制度
A28: {考勤方式} | B28: 考勤方式与系统 | D28: 打卡机 / 钉钉 / 纸质?数据能否导出留存? | E28: 考勤制度、证据体系
A29: {用工形式} | B29: 涉及的用工形式 | D29: 全日制 / 非全 / 派遣 / 外包 / 返聘 / 实习 / 灵活 | E29: 用工形式方案、各类协议
A30: 四、薪酬与发放
A31: {薪酬结构} | B31: 薪酬结构科目 | D31: ★ 基本工资 / 绩效 / 津贴 / 补贴 —— 各科目名称与占比 | E31: 薪酬制度、社保基数、加班费基数
A32: {发薪日} | B32: 发薪日 | D32: 每月几号发上月工资 | E32: 劳动合同、薪酬制度
A33: {发薪方式} | B33: 发薪方式 | D33: 对公代发 / 现金 / 私卡?(现金私卡 → 高危) | E33: 薪酬制度、三表一致方案
A34: {加班费基数} | B34: 加班费计算基数口径 | D34: 按全额 / 按基本工资?(注意地方差异) | E34: 加班费方案、劳动合同
A35: {现有福利项} | B35: 现有福利项目 | D35: 防暑降温费 / 企业年金 / 困难补助 / 餐补 / 通讯补… | E35: 社保基数排除方案
A36: 五、制度与民主程序
A37: {有无工会} | B37: 是否设工会 / 职代会 | D37: ★ 决定民主程序走哪条路径 | E37: 民主程序文书包
A38: {职工代表} | B38: 职工代表人数与产生方式 | D38: 无工会时,民主程序须靠职工代表大会 | E38: 民主程序文书包
A39: {现有制度} | B39: 现有制度清单 | D39: 有哪些?何时订的?走没走民主程序?公示了吗? | E39: 制度合法化改造
A40: {制度生效日} | B40: 新制度拟生效日 | E40: 制度发布公告、签收表
A41: {公示方式} | B41: 公示告知方式 | D41: 公告栏 / 邮件 / OA / 培训?能否留痕? | E41: 公示留痕方案
A42: 六、组织与业务场景
A43: {行业} | B43: 所属行业 | D43: 决定行业模块与职业病风险 | E43: 制度行业模块、职业病方案
A44: {部门岗位} | B44: 部门与岗位清单 | E44: 岗位说明书、涉密岗位清单
A45: {职业病岗位} | B45: 是否涉职业病 / 特殊作业 | D45: 粉尘 / 噪音 / 高温 / 化学品? → L1 立即处理 | E45: 职业病防治方案、体检台账
A46: {涉密岗位} | B46: 核心 / 涉密 / 高管岗位 | D46: 决定 L4 资产保护层是否启动 | E46: 保密协议、竞业协议
A47: {淡旺季} | B47: 是否有明显淡旺季 | D47: 影响用工形式与加班安排 | E47: 用工形式方案
A48: 七、历史与既往
A49: {既往争议} | B49: 近三年仲裁 / 诉讼 | D49: 起数、争议焦点、结果 | E49: 风险预判、整改重点
A50: {行政处罚} | B50: 是否被监察 / 稽查 / 处罚 | D50: ★ 有 = 已点火,转风控线优先 | E50: 急症判定
A51: {历史敞口} | B51: 社保历史欠缴大致规模 | D51: 近三年未保 / 低基数敞口 | E51: 过渡方案、成本测算

Sheet 十大板块诊断主表
A1: 十大板块诊断主表 V2 —— 诊断 + 交付分流 合一
A2: 填完 K 列「现状判定」→ L/M/N/O 列直接告诉你:这项该交付什么、属哪一层、排第几期。判定为「合规」的行可忽略后四列。
A4: 序号 | B4: 板块 | C4: 管控要点 | D4: 维度 | E4: 法规依据 | F4: 合规规范要求(应然) | G4: 常见风险点 | H4: 诊断/核查问题(现场) | I4: 现状记录 | J4: 固有风险 | K4: 现状判定 | L4: 【风控】分流 | M4: 【风控】交付物 | N4: 【合规】层级 | O4: 【合规】建议期次 | P4: 备注/提示 | Q4: ★数
A5: ①招聘入职管控 （13 项）
A6: 1 | B6: ①招聘入职管控 | C6: 招聘信息合规 | D6: 法·管 | E6: 《就业促进法》第3/26条；《关于规范招聘行为促进妇女就业的通知》 | F6: 招聘信息不得含性别、民族、年龄、户籍、婚育等歧视性条件 | G6: 广告含歧视性表述，遭投诉，面临1万-5万元罚款及诉讼 | H6: 招聘渠道有哪些？广告谁审核？有无性别/年龄/婚育限制？ | J6: ★★☆☆☆ | L6: T | M6: 招聘信息模板(删歧视表述) | N6: L0 事件型 | O6: 备用·用到再补 | Q6: =LEN(J6)-LEN(SUBSTITUTE(J6,"★","")) -> 2
A7: 2 | B7: ①招聘入职管控 | C7: 录用条件书面化 | D7: 法·人 | E7: 《劳动合同法》第39条、第21条 | F7: 录用条件应事前书面明确并经员工确认，作为试用期解除依据 | G7: 录用条件不明，试用期「不符合录用条件」无法举证解除 | H7: 有无书面录用条件并让员工签字确认？试用期如何考核？ | J7: ★★★★☆ | L7: T | M7: 录用条件确认书 | N7: L2 证据能力 | O7: 一期·证据 | P7: 试用期解除的举证基础 | Q7: =LEN(J7)-LEN(SUBSTITUTE(J7,"★","")) -> 4
A8: 3 | B8: ①招聘入职管控 | C8: 录用通知书 | D8: 法·业 | E8: 《劳动合同法》；《民法典》缔约过失责任 | F8: offer应设单方撤回条件，薪资岗位不宜写死、与合同一致 | G8: offer发出后撤回构成缔约过失；offer与合同条款冲突 | H8: 发录用通知书吗？写了哪些内容？能否撤回？ | J8: ★★★☆☆ | L8: T | M8: 录用通知书模板(设撤回条款) | N8: L0 事件型 | O8: 备用·用到再补 | Q8: =LEN(J8)-LEN(SUBSTITUTE(J8,"★","")) -> 3
A9: 4 | B9: ①招聘入职管控 | C9: 如实告知与入职登记 | D9: 法·人 | E9: 《劳动合同法》第8条、第26条 | F9: 员工负如实说明义务；企业建立花名册并留存登记 | G9: 简历/资历造假却无「如实告知」条款，难以据此解除 | H9: 入职填登记表吗？有无如实告知条款与签字？核验真实性吗？ | J9: ★★★★☆ | L9: T | M9: 入职申请表 / 如实告知书 | N9: L2 证据能力 | O9: 一期·证据 | Q9: =LEN(J9)-LEN(SUBSTITUTE(J9,"★","")) -> 4
A10: 5 | B10: ①招聘入职管控 | C10: 离职证明核验 | D10: 法·业 | E10: 《劳动合同法》第91条 | F10: 录用应核验前单位离职证明，避免招用未解除劳动关系者 | G10: 未收离职证明，与原单位形成双重用工，承担连带赔偿 | H10: 要求提供离职证明吗？没有的怎么处理？ | J10: ★★★★☆ | L10: T | M10: 无离职证明承诺书 | N10: L0 事件型 | O10: 备用·用到再补 | Q10: =LEN(J10)-LEN(SUBSTITUTE(J10,"★","")) -> 4
A11: 6 | B11: ①招聘入职管控 | C11: 背景调查授权 | D11: 法·人 | E11: 《个人信息保护法》 | F11: 背调须经书面授权并限定范围，第三方机构签保密协议 | G11: 未授权/超范围背调侵犯个人信息；信息泄露担责 | H11: 重要岗位做背调吗？有书面授权吗？谁来做？ | J11: ★★★★★ | L11: T | M11: 背景调查授权书 | N11: L0 事件型 | O11: 备用·用到再补 | Q11: =LEN(J11)-LEN(SUBSTITUTE(J11,"★","")) -> 5
A12: 7 | B12: ①招聘入职管控 | C12: 入职体检/健康证 | D12: 业·人 | E12: 《职业病防治法》；《食品安全法》 | F12: 涉职业病岗位岗前体检；食品/特定岗位办健康证 | G12: 带病/带伤入职后主张职业病、工伤；无健康证行政处罚 | H12: 入职做体检吗？涉职业病/餐饮岗位有健康证吗？ | J12: ★★★☆☆ | L12: P | M12: 体检告知书 + 健康证台账 | N12: L0 事件型 | O12: 备用·用到再补 | P12: 涉职业病岗位→并入 L1 工伤 | Q12: =LEN(J12)-LEN(SUBSTITUTE(J12,"★","")) -> 3
A13: 8 | B13: ①招聘入职管控 | C13: 三期女职工识别 | D13: 法·管 | E13: 《妇女权益保障法》；《女职工劳动保护特别规定》 | F13: 不得因婚育拒录或解除，合规处理三期员工 | G13: 已孕女职工入职后才知情，三期保护下进退两难 | H13: 入职是否了解婚育/三期情况？如何合规处理？ | J13: ★★★☆☆ | L13: T | M13: 入职合规告知 | N13: L0 事件型 | O13: 备用·用到再补 | Q13: =LEN(J13)-LEN(SUBSTITUTE(J13,"★","")) -> 3
A14: 9 | B14: ①招聘入职管控 | C14: 用工主体一致性 | D14: 业·税·法 | E14: 《劳动合同法》 | F14: 招聘、签约、发薪、参保主体保持一致 | G14: 多主体混同用工，关系不清、连带责任、三表不符 | H14: 谁招的？跟谁签合同？谁发薪、谁交社保？ | J14: ★★★★☆ | L14: S | M14: 主体架构梳理方案 | N14: L3 结构 | O14: 二期·结构 | P14: ★核心:招/签/发/保是否同一主体 | Q14: =LEN(J14)-LEN(SUBSTITUTE(J14,"★","")) -> 4
A15: 10 | B15: ①招聘入职管控 | C15: 入职流程归口 | D15: 管·人 | E15: 《劳动合同法》第10条 | F15: 入职由HR统一办理、限定时限、全程留痕 | G15: 部门私自录用、超1个月才上报，漏签合同、漏缴社保 | H15: 入职谁办理？有无超1个月才上报上岗的情况？ | J15: ★★★★☆ | L15: P | M15: 入职办理SOP + 台账 | N15: L2 证据能力 | O15: 一期·证据 | Q15: =LEN(J15)-LEN(SUBSTITUTE(J15,"★","")) -> 4
A16: 11 | B16: ①招聘入职管控 | C16: 个人信息收集合规 | D16: 法·管 | E16: 《个人信息保护法》第6/13条；《劳动合同法》第8条 | F16: 入职信息收集遵循最小必要，敏感信息单独告知并取得同意，不超范围 | G16: 违规收集/留存身份证、人脸等敏感信息，被投诉或泄露担责 | H16: 入职表收集哪些信息？是否告知用途并取得同意？证件如何留存？ | J16: ★★★☆☆ | L16: T | M16: 信息收集告知同意书 | N16: L2 证据能力 | O16: 一期·证据 | Q16: =LEN(J16)-LEN(SUBSTITUTE(J16,"★","")) -> 3
A17: 12 | B17: ①招聘入职管控 | C17: 资质与证件核验 | D17: 法·业 | E17: 《劳动合同法》；特种作业/从业资格相关规定 | F17: 特种作业、专业资格岗位须核验有效证书并留存 | G17: 无证上岗、证书造假，发生事故企业担责、行政处罚 | H17: 哪些岗位需持证？入职是否核验留存？证书是否有效？ | J17: ★★★☆☆ | L17: P | M17: 持证上岗清单 + 核验留痕 | N17: L0 事件型 | O17: 备用·用到再补 | Q17: =LEN(J17)-LEN(SUBSTITUTE(J17,"★","")) -> 3
A18: 13 | B18: ①招聘入职管控 | C18: 岗前安全与岗位告知 | D18: 法·业 | E18: 《安全生产法》第28条；《职业病防治法》 | F18: 上岗前进行安全/职业卫生培训与岗位风险告知并签字 | G18: 未培训上岗发生工伤/职业病，企业过错放大赔偿 | H18: 新员工上岗前是否做安全教育？有无签字记录？ | J18: ★★★☆☆ | L18: P | M18: 三级安全教育 + 签到表 | N18: L1 负债型 | O18: ★立即 | P18: 工伤第一道防线 | Q18: =LEN(J18)-LEN(SUBSTITUTE(J18,"★","")) -> 3
A19: ②劳动关系管控 （28 项）
A20: 14 | B20: ②劳动关系管控 | C20: 书面合同及时性 | D20: 法·人 | E20: 《劳动合同法》第10条、第82条 | F20: 用工之日起1个月内订立书面劳动合同 | G20: 满1个月未签→每月二倍工资（最长11个月）；满1年视为无固定期限 | H20: 全员都签合同了吗？入职多久签？有无超1年未签的？ | J20: ★★★★★ | L20: P | M20: 入职即签流程 + 签订台账 | N20: L1 负债型 | O20: ★立即 | P20: 未签每天长双倍工资;存量未签→转 S 个案 | Q20: =LEN(J20)-LEN(SUBSTITUTE(J20,"★","")) -> 5
A21: 15 | B21: ②劳动关系管控 | C21: 合同版本与必备条款 | D21: 法 | E21: 《劳动合同法》第17条 | F21: 合同含必备条款：期限、岗位、地点、工时、报酬、社保等 | G21: 用人社/网络模板，缺必备条款或含违法条款 | H21: 合同用什么版本？人社模板/律师审核/网上下载？ | J21: ★★★★☆ | L21: T | M21: 合规劳动合同模板 | N21: L2 证据能力 | O21: 一期·证据 | Q21: =LEN(J21)-LEN(SUBSTITUTE(J21,"★","")) -> 4
A22: 16 | B22: ②劳动关系管控 | C22: 工作地点与岗位约定 | D22: 法·业 | E22: 《劳动合同法》第17/35条 | F22: 合理约定工作地点与岗位，预留调整空间 | G22: 约定过死无法调岗调地点；约定过宽被认定不明 | H22: 合同里工作地点、岗位怎么写的？能否调整？ | J22: ★★★☆☆ | L22: T | M22: 弹性地点/岗位条款 | N22: L2 证据能力 | O22: 一期·证据 | Q22: =LEN(J22)-LEN(SUBSTITUTE(J22,"★","")) -> 3
A23: 17 | B23: ②劳动关系管控 | C23: 工时制度约定 | D23: 法 | E23: 《劳动合同法》；《劳动法》第36-39条 | F23: 明确工时制度；特殊工时须经审批 | G23: 约定单休/六天/对企业不利条款，加班费风险 | H23: 合同约定的工时？有无单休、对企业不利的条款？ | J23: ★★★★☆ | L23: T | M23: 工时条款 | N23: L1 负债型 | O23: 三期·负债 | Q23: =LEN(J23)-LEN(SUBSTITUTE(J23,"★","")) -> 4
A24: 18 | B24: ②劳动关系管控 | C24: 工资约定 | D24: 法·税 | E24: 《劳动合同法》第17条；《最低工资规定》 | F24: 工资约定明确、不低于最低工资；加班费基数依法 | G24: 工资约定不明/低于最低工资；加班费基数被做高 | H24: 合同工资怎么约定的？加班费基数如何确定？ | J24: ★★★★☆ | L24: T | M24: 工资条款(结构与口径) | N24: L3 结构 | O24: 二期·结构 | P24: 依赖第70项薪酬结构设计 | Q24: =LEN(J24)-LEN(SUBSTITUTE(J24,"★","")) -> 4
A25: 19 | B25: ②劳动关系管控 | C25: 法律文书送达地址 | D25: 法·管 | E25: 《劳动合同法》；《民事诉讼法》送达规则 | F25: 合同约定法律文书送达地址条款 | G25: 无送达地址，解除/通知无法有效送达，程序瑕疵 | H25: 合同里写了文书送达地址吗？ | J25: ★★★☆☆ | L25: T | M25: 送达地址确认书 | N25: L2 证据能力 | O25: 一期·证据 | P25: 低成本高价值 | Q25: =LEN(J25)-LEN(SUBSTITUTE(J25,"★","")) -> 3
A26: 20 | B26: ②劳动关系管控 | C26: 签署规范 | D26: 法 | E26: 《劳动合同法》第16条 | F26: 本人签署、骑缝、无空白，禁止代签 | G26: 代签无效、空白被篡改、换页风险 | H26: 有无代签、带回家签、空白合同、未按骑缝？ | J26: ★★★★☆ | L26: P | M26: 签署操作规范 + 培训 | N26: L2 证据能力 | O26: 一期·证据 | Q26: =LEN(J26)-LEN(SUBSTITUTE(J26,"★","")) -> 4
A27: 21 | B27: ②劳动关系管控 | C27: 交付与签收 | D27: 法 | E27: 《劳动合同法》第16条 | F27: 合同一式两份，交付员工并留签收记录 | G27: 未交付/未签收，员工否认，举证不能 | H27: 合同发给员工了吗？有领取签收吗？ | J27: ★★★☆☆ | L27: P | M27: 合同领取签收表 + 流程 | N27: L2 证据能力 | O27: 一期·证据 | Q27: =LEN(J27)-LEN(SUBSTITUTE(J27,"★","")) -> 3
A28: 22 | B28: ②劳动关系管控 | C28: 续签管理 | D28: 法·人 | E28: 《劳动合同法》第14条 | F28: 到期前及时续签，管控无固定期限触发 | G28: 到期未续形成事实用工/二倍工资；二次固定期限后须签无固定期限 | H28: 到期合同如何续签？有无该签无固定期限的？ | J28: ★★★★☆ | L28: P | M28: 到期预警流程 + 期限征询表 | N28: L2 证据能力 | O28: 一期·证据 | Q28: =LEN(J28)-LEN(SUBSTITUTE(J28,"★","")) -> 4
A29: 23 | B29: ②劳动关系管控 | C29: 试用期约定 | D29: 法·人 | E29: 《劳动合同法》第19/20条 | F29: 试用期期限合法，工资不低于约定80%且不低于最低工资 | G29: 试用期过长/重复约定/工资过低；超期违法 | H29: 试用期多久？工资多少？有无延长试用期？ | J29: ★★★★★ | L29: T | M29: 试用期条款(法定上限) | N29: L1 负债型 | O29: ★立即 | P29: 违法约定按已履行期每月赔一倍 | Q29: =LEN(J29)-LEN(SUBSTITUTE(J29,"★","")) -> 5
A30: 24 | B30: ②劳动关系管控 | C30: 保密与知识产权 | D30: 法·业 | E30: 《劳动合同法》第23条；《反不正当竞争法》 | F30: 涉密岗位签保密协议，明确职务成果权属 | G30: 涉密岗位未签保密/权属约定，技术外泄 | H30: 涉密/核心岗位签保密协议了吗？职务成果归属约定了吗？ | J30: ★★★★☆ | L30: T | M30: 保密协议 / 权属协议 | N30: L4 资产保护 | O30: 选配·按业务 | P30: 技术/销售型必做 | Q30: =LEN(J30)-LEN(SUBSTITUTE(J30,"★","")) -> 4
A31: 25 | B31: ②劳动关系管控 | C31: 合同保管 | D31: 管 | E31: 《劳动合同法》 | F31: 合同集中、安全保管，防丢失 | G31: 合同遗失，企业留存缺失，举证不利 | H31: 合同谁保管？是否完整归档？ | J31: ★★☆☆☆ | L31: P | M31: 合同台账 + 归档 | N31: L2 证据能力 | O31: 一期·证据 | Q31: =LEN(J31)-LEN(SUBSTITUTE(J31,"★","")) -> 2
A32: 26 | B32: ②劳动关系管控 | C32: 电子劳动合同合规 | D32: 法·管 | E32: 《劳动合同法》第3/16条；人社部电子劳动合同订立指引 | F32: 采用符合可靠电子签名要求的平台订立，可生成存储可验证 | G32: 电子合同签署不规范、无法验证，被认定未订立书面合同 | H32: 是否使用电子合同？用什么平台？能否导出验证？ | J32: ★★★☆☆ | L32: P | M32: 电子合同管理规范 | N32: L2 证据能力 | O32: 一期·证据 | Q32: =LEN(J32)-LEN(SUBSTITUTE(J32,"★","")) -> 3
A33: 27 | B33: ②劳动关系管控 | C33: 岗位说明书与录用条件衔接 | D33: 法·管 | E33: 《劳动合同法》第39/40条 | F33: 岗位职责、任职要求、录用条件书面化并与合同制度衔接 | G33: JD缺失，'不胜任'与'不符合录用条件'解除无标准 | H33: 各岗位有无岗位说明书？与录用条件、考核如何衔接？ | J33: ★★★☆☆ | L33: T | M33: 岗位说明书模板 | N33: L2 证据能力 | O33: 一期·证据 | Q33: =LEN(J33)-LEN(SUBSTITUTE(J33,"★","")) -> 3
A34: 28 | B34: ②劳动关系管控 | C34: 集体合同管理 | D34: 法·管 | E34: 《劳动合同法》第51-56条；《集体合同规定》 | F34: 依法订立并履行集体合同/专项集体合同 | G34: 应签未签集体合同、内容与个别合同冲突 | H34: 是否签订集体合同？内容是否与现行制度一致？ | J34: ★★☆☆☆ | L34: T | M34: 集体合同范本 | N34: L0 事件型 | O34: 备用·用到再补 | Q34: =LEN(J34)-LEN(SUBSTITUTE(J34,"★","")) -> 2
A35: （特殊用工关系 · 兼职 / 劳务派遣 / 外包 / 退休返聘 / 超龄 / 实习 / 非全日制等，均属特殊劳动关系）
A36: 29 | B36: ②劳动关系管控 | C36: 劳务派遣比例 | D36: 法·业 | E36: 《劳务派遣暂行规定》第4/28条 | F36: 派遣不超用工总量10%，限临时性/辅助性/替代性岗位 | G36: 超比例/非三性岗位违规 | H36: 用派遣吗？什么岗位？占比多少？ | J36: ★★★★☆ | L36: S | M36: 派遣结构调整方案 | N36: L3 结构 | O36: 二期·结构 | P36: 10%比例 + 三性岗位 | Q36: =LEN(J36)-LEN(SUBSTITUTE(J36,"★","")) -> 4
A37: 30 | B37: ②劳动关系管控 | C37: 假外包真派遣 | D37: 法·业 | E37: 《劳务派遣暂行规定》第27条 | F37: 外包须真实，由承包方组织管理与发薪 | G37: 假外包被认定与用工单位存在劳动关系 | H37: 外包/承包怎么管理、谁发薪？ | J37: ★★★★★ | L37: S | M37: 外包边界重构方案 + 承包协议 | N37: L3 结构 | O37: 二期·结构 | P37: ★高危结构问题 | Q37: =LEN(J37)-LEN(SUBSTITUTE(J37,"★","")) -> 5
A38: 31 | B38: ②劳动关系管控 | C38: 退休返聘 | D38: 法 | E38: 人社部令第56号；《民法典》 | F38: 返聘签劳务协议，明确工伤等责任 | G38: 未签协议/工伤责任不清独担 | H38: 返聘人员签协议了吗？工伤怎么办？ | J38: ★★★★☆ | L38: S | M38: 返聘协议 + 保障安排 | N38: L1 负债型 | O38: ★立即 | P38: 人社部令第56号已生效,协议与工伤保障须重新评估 | Q38: =LEN(J38)-LEN(SUBSTITUTE(J38,"★","")) -> 4
A39: 32 | B39: ②劳动关系管控 | C39: 非全日制 | D39: 法 | E39: 《劳动合同法》第68-72条 | F39: 每日≤4小时、每周≤24小时 | G39: 超时被认定全日制，补社保与合同 | H39: 兼职每天/每周工作多久？ | J39: ★★★☆☆ | L39: P | M39: 非全日制合同 + 工时管控 | N39: L3 结构 | O39: 二期·结构 | P39: 工时超限即转全日制 | Q39: =LEN(J39)-LEN(SUBSTITUTE(J39,"★","")) -> 3
A40: 33 | B40: ②劳动关系管控 | C40: 实习生 | D40: 法·业 | E40: 实习用工相关规定 | F40: 签实习协议并购买意外险 | G40: 未签协议/未保险，受伤担责 | H40: 用实习生吗？签协议、买保险了吗？ | J40: ★★★☆☆ | L40: T | M40: 实习协议 + 意外险 | N40: L0 事件型 | O40: 备用·用到再补 | Q40: =LEN(J40)-LEN(SUBSTITUTE(J40,"★","")) -> 3
A41: 34 | B41: ②劳动关系管控 | C41: 劳务/承揽区分 | D41: 法 | E41: 《民法典》；《劳动合同法》 | F41: 劳务、承揽关系与劳动关系严格区分 | G41: 名为劳务实为劳动→补缴+责任 | H41: 哪些是劳务/承揽合作？ | J41: ★★★★☆ | L41: S | M41: 用工关系性质厘清方案 | N41: L3 结构 | O41: 二期·结构 | Q41: =LEN(J41)-LEN(SUBSTITUTE(J41,"★","")) -> 4
A42: 35 | B42: ②劳动关系管控 | C42: 灵活用工/平台 | D42: 法·税 | E42: 平台用工与税收政策 | F42: 业务真实、四流一致、税务合规 | G42: 假灵活用工虚开发票、关系认定 | H42: 用平台/灵活用工吗？怎么结算开票？ | J42: ★★★★☆ | L42: S | M42: 灵活用工合规设计(四流一致) | N42: L3 结构 | O42: 二期·结构 | Q42: =LEN(J42)-LEN(SUBSTITUTE(J42,"★","")) -> 4
A43: 36 | B43: ②劳动关系管控 | C43: 借调/共享用工 | D43: 法·管 | E43: 相关规定 | F43: 借调协议明确工资、工伤、管理责任 | G43: 责任不清，争议归属难 | H43: 有借调/共享用工吗？ | J43: ★★☆☆☆ | L43: T | M43: 借调协议 | N43: L0 事件型 | O43: 备用·用到再补 | Q43: =LEN(J43)-LEN(SUBSTITUTE(J43,"★","")) -> 2
A44: 37 | B44: ②劳动关系管控 | C44: 童工/未成年工 | D44: 法 | E44: 《禁止使用童工规定》；未成年工特殊保护规定 | F44: 禁用未满16周岁；未成年工特殊保护与体检 | G44: 使用童工→重罚乃至刑责 | H44: 有无16-18岁或疑似低龄人员？ | J44: ★★★★★ | L44: P | M44: 核验流程 + 禁用红线 | N44: L0 事件型 | O44: ★立即 | P44: ★红线:发现即停,无分期空间 | Q44: =LEN(J44)-LEN(SUBSTITUTE(J44,"★","")) -> 5
A45: 38 | B45: ②劳动关系管控 | C45: 季节性用工 | D45: 法·业 | E45: 《劳动合同法》 | F45: 季节/临时用工签合同、及时参保 | G45: 入离职扎堆漏签漏保 | H45: 旺季临时工怎么签、怎么保？ | J45: ★★★☆☆ | L45: P | M45: 季节用工手续规范 | N45: L0 事件型 | O45: 备用·用到再补 | Q45: =LEN(J45)-LEN(SUBSTITUTE(J45,"★","")) -> 3
A46: 39 | B46: ②劳动关系管控 | C46: 司机/食堂等特殊岗 | D46: 法·业 | E46: 相关规定 | F46: 司机、食堂等明确用工关系、协议与资质 | G46: 关系不清、健康证缺失担责 | H46: 有司机/食堂吗？怎么管理？ | J46: ★★☆☆☆ | L46: T | M46: 特殊岗位用工规范 | N46: L0 事件型 | O46: 备用·用到再补 | Q46: =LEN(J46)-LEN(SUBSTITUTE(J46,"★","")) -> 2
A47: 40 | B47: ②劳动关系管控 | C47: 用工形式整体合规设计 | D47: 法·业 | E47: 综合 | F47: 按业务需要合法选择并组合用工形式，避免错配与规避 | G47: 用工形式错配/以合作之名规避用工责任 | H47: 各类用工形式占比与原因？是否存在规避？ | J47: ★★★☆☆ | L47: S | M47: 用工形式设计方案 | N47: L3 结构 | O47: 二期·结构 | P47: ★★核心:结构层的总纲 | Q47: =LEN(J47)-LEN(SUBSTITUTE(J47,"★","")) -> 3
A48: 41 | B48: ②劳动关系管控 | C48: 外包供应商资质与管理 | D48: 法·管 | E48: 《劳动合同法》；外包相关规定 | F48: 外包须真实、有资质、自主管理，界面清晰 | G48: 假外包真派遣、供应商无资质，连带担责 | H48: 外包供应商资质？现场谁管理、谁发薪？ | J48: ★★★★☆ | L48: P | M48: 外包管理规范 + 协议 | N48: L3 结构 | O48: 二期·结构 | Q48: =LEN(J48)-LEN(SUBSTITUTE(J48,"★","")) -> 4
A49: ③考勤休假管控 （15 项）
A50: 42 | B50: ③考勤休假管控 | C50: 工时制度合法 | D50: 法 | E50: 《劳动法》第36条；《国务院关于职工工作时间的规定》 | F50: 标准工时每日8小时、每周40小时 | G50: 超时用工未付加班费，工时违法 | H50: 作息时间怎样？每天工作几小时？周休几天？ | J50: ★★★★☆ | L50: S | M50: 工时制度核定方案 | N50: L1 负债型 | O50: 三期·负债 | Q50: =LEN(J50)-LEN(SUBSTITUTE(J50,"★","")) -> 4
A51: 43 | B51: ③考勤休假管控 | C51: 特殊工时审批 | D51: 法·业 | E51: 《劳动法》第39条；地方综合/不定时工时审批规定 | F51: 综合/不定时工时须经人社部门审批 | G51: 未批擅自适用→一律按标准工时计加班 | H51: 是否使用综合/不定时工时？有审批吗？ | J51: ★★★★★ | L51: S | M51: 特殊工时申报方案 | N51: L1 负债型 | O51: 三期·负债 | P51: 需当地审批,周期长,尽早启动 | Q51: =LEN(J51)-LEN(SUBSTITUTE(J51,"★","")) -> 5
A52: 44 | B52: ③考勤休假管控 | C52: 加班审批制度 | D52: 法·管 | E52: 《劳动合同法》第31条 | F52: 建立加班申请审批制度，加班需经批准 | G52: 默许加班无审批，加班费追溯、举证不利 | H52: 加班要审批吗？有无加班审批记录？ | J52: ★★★★☆ | L52: P | M52: 加班审批表 + 流程 | N52: L2 证据能力 | O52: 一期·证据 | P52: ★加班举证的关键 | Q52: =LEN(J52)-LEN(SUBSTITUTE(J52,"★","")) -> 4
A53: 45 | B53: ③考勤休假管控 | C53: 加班费标准 | D53: 法·税 | E53: 《劳动法》第44条 | F53: 平日150%、休息日200%、法定节假日300% | G53: 加班费未足额、基数偏低，集体追溯 | H53: 加班费怎么算？基数是多少？ | J53: ★★★★☆ | L53: S | M53: 加班费核算方案 | N53: L1 负债型 | O53: 三期·负债 | P53: ★时效内持续累积 | Q53: =LEN(J53)-LEN(SUBSTITUTE(J53,"★","")) -> 4
A54: 46 | B54: ③考勤休假管控 | C54: 考勤记录留存 | D54: 法·管 | E54: 《劳动争议司法解释（一）》举证规则 | F54: 考勤记录由企业保存（至少2年），完整可追溯 | G54: 考勤不规范，加班举证责任归企业而败诉 | H54: 用什么考勤？记录完整吗？保存多久？ | J54: ★★★★☆ | L54: P | M54: 考勤系统 + 留存规范 | N54: L2 证据能力 | O54: 一期·证据 | P54: ★★证据能力核心 | Q54: =LEN(J54)-LEN(SUBSTITUTE(J54,"★","")) -> 4
A55: 47 | B55: ③考勤休假管控 | C55: 年休假 | D55: 法·人 | E55: 《职工带薪年休假条例》第5条 | F55: 依工龄给年休假；应休未休按日工资300%支付 | G55: 应休未休未支付300%报酬 | H55: 年休假怎么安排？未休的如何处理？ | J55: ★★★☆☆ | L55: P | M55: 年休假台账 + 落实 | N55: L1 负债型 | O55: 三期·负债 | P55: 未休需付300% | Q55: =LEN(J55)-LEN(SUBSTITUTE(J55,"★","")) -> 3
A56: 48 | B56: ③考勤休假管控 | C56: 法定节假日 | D56: 法 | E56: 《全国年节及纪念日放假办法》；《劳动法》第44条 | F56: 法定节假日加班按300%支付，不得调休抵充 | G56: 法定节假日加班未付300% | H56: 法定节假日加班怎么处理？ | J56: ★★★☆☆ | L56: P | M56: 节假日加班核算规则 | N56: L1 负债型 | O56: 三期·负债 | Q56: =LEN(J56)-LEN(SUBSTITUTE(J56,"★","")) -> 3
A57: 49 | B57: ③考勤休假管控 | C57: 病假与医疗期 | D57: 法·人 | E57: 《企业职工患病或非因工负伤医疗期规定》 | F57: 依法给予医疗期，病假工资不低于最低工资80% | G57: 病假工资过低；医疗期内违法解除 | H57: 病假工资怎么发？医疗期如何计算？ | J57: ★★★☆☆ | L57: P | M57: 病假工资与医疗期规则 | N57: L2 证据能力 | O57: 一期·证据 | Q57: =LEN(J57)-LEN(SUBSTITUTE(J57,"★","")) -> 3
A58: 50 | B58: ③考勤休假管控 | C58: 三期与婚育假 | D58: 法·人 | E58: 《女职工劳动保护特别规定》；地方人口与计生条例 | F58: 落实产假/陪产假/育儿假等地方标准（如部分地区产假158天） | G58: 婚育假未给足，差额补偿与投诉 | H58: 产假/陪产假/育儿假按什么标准执行？ | J58: ★★★☆☆ | L58: P | M58: 假期管理表(对照地方标准) | N58: L2 证据能力 | O58: 一期·证据 | Q58: =LEN(J58)-LEN(SUBSTITUTE(J58,"★","")) -> 3
A59: 51 | B59: ③考勤休假管控 | C59: 隐性加班 | D59: 法·业 | E59: 司法实践（线上加班认定） | F59: 对下班后持续性线上工作合理管理与界定 | G59: 下班后微信/钉钉处理工作被认定加班 | H59: 下班后是否要求员工线上处理工作？ | J59: ★★★☆☆ | L59: S | M59: 线上响应边界规则设计 | N59: L1 负债型 | O59: 三期·负债 | P59: 新兴争议高发点 | Q59: =LEN(J59)-LEN(SUBSTITUTE(J59,"★","")) -> 3
A60: 52 | B60: ③考勤休假管控 | C60: 调休管理 | D60: 法·管 | E60: 《劳动法》 | F60: 调休规则合法，不得跨年清零或强制抵加班费 | G60: 调休跨年清零、强制调休抵加班费违法 | H60: 调休怎么规定的？会跨年清零吗？ | J60: ★★☆☆☆ | L60: T | M60: 调休规则条款 | N60: L2 证据能力 | O60: 一期·证据 | Q60: =LEN(J60)-LEN(SUBSTITUTE(J60,"★","")) -> 2
A61: 53 | B61: ③考勤休假管控 | C61: 综合工时加班核算 | D61: 法·人 | E61: 《劳动法》第41条；综合计算工时工作制规定 | F61: 综合工时以周期总工时核算，超出部分付1.5倍加班费 | G61: 综合工时下不付或少付加班费，周期超时 | H61: 综合工时岗位如何核算加班？周期总工时是否超标？ | J61: ★★★☆☆ | L61: S | M61: 综合工时核算模型 | N61: L1 负债型 | O61: 三期·负债 | Q61: =LEN(J61)-LEN(SUBSTITUTE(J61,"★","")) -> 3
A62: 54 | B62: ③考勤休假管控 | C62: 值班与加班区分 | D62: 法·管 | E62: 加班费相关裁审口径 | F62: 非生产经营性值班与加班区分，值班按值班待遇 | G62: 将加班混为值班规避加班费，被追溯 | H62: 是否安排值班？值班与加班如何区分、如何计酬？ | J62: ★★☆☆☆ | L62: T | M62: 值班管理制度 | N62: L2 证据能力 | O62: 一期·证据 | Q62: =LEN(J62)-LEN(SUBSTITUTE(J62,"★","")) -> 2
A63: 55 | B63: ③考勤休假管控 | C63: 年休假折算与离职结算 | D63: 法·人 | E63: 《职工带薪年休假条例》及实施办法 | F63: 入职首年/离职当年按比例折算，离职结清未休年假报酬 | G63: 折算错误、离职未结清未休年假，被追300% | H63: 年休假如何折算？离职时未休年假如何结算？ | J63: ★★★☆☆ | L63: P | M63: 年休假台账 + 结算规则 | N63: L1 负债型 | O63: 三期·负债 | Q63: =LEN(J63)-LEN(SUBSTITUTE(J63,"★","")) -> 3
A64: 56 | B64: ③考勤休假管控 | C64: 事假与旷工认定 | D64: 管·法 | E64: 规章制度；裁审口径 | F64: 事假、旷工的认定标准、审批与扣薪规则明确合法 | G64: 旷工认定无依据、据此解除被认定违法 | H64: 事假怎么批？旷工怎么认定？连续旷工多少天可解除？ | J64: ★★★☆☆ | L64: T | M64: 考勤管理制度条款 | N64: L2 证据能力 | O64: 一期·证据 | Q64: =LEN(J64)-LEN(SUBSTITUTE(J64,"★","")) -> 3
A65: ④规章制度管控 （13 项）
A66: 57 | B66: ④规章制度管控 | C66: 制度体系完整 | D66: 法·管 | E66: 《劳动合同法》第4条 | F66: 建立奖惩、考勤、薪酬等核心制度，作为管理依据 | G66: 制度缺失，处罚、解除无依据 | H66: 有哪些规章制度？奖惩、考勤、薪酬制度齐全吗？ | J66: ★★★★☆ | L66: T | M66: 规章制度全套模板 | N66: L2 证据能力 | O66: 一期·证据 | P66: ★★核心产品 | Q66: =LEN(J66)-LEN(SUBSTITUTE(J66,"★","")) -> 4
A67: 58 | B67: ④规章制度管控 | C67: 民主程序 | D67: 法 | E67: 《劳动合同法》第4条 | F67: 涉切身利益制度须经职代会/全体职工讨论 | G67: 未经民主程序→程序违法、对员工无效 | H67: 制度制定时开过职代会/职工大会吗？有证据吗？ | J67: ★★★★★ | L67: P | M67: 民主程序全套资料 + 现场执行 | N67: L2 证据能力 | O67: 一期·证据 | P67: ★★★不执行=制度无效;必须陪跑 | Q67: =LEN(J67)-LEN(SUBSTITUTE(J67,"★","")) -> 5
A68: 59 | B68: ④规章制度管控 | C68: 公示告知 | D68: 法 | E68: 《劳动合同法》第4条 | F68: 制度须向员工公示或告知 | G68: 未公示告知→不能作为处罚/解除依据 | H68: 制度怎么公示告知的？有签字/培训记录吗？ | J68: ★★★★★ | L68: P | M68: 公示留痕 + 培训签到 | N68: L2 证据能力 | O68: 一期·证据 | P68: ★★★同上 | Q68: =LEN(J68)-LEN(SUBSTITUTE(J68,"★","")) -> 5
A69: 60 | B69: ④规章制度管控 | C69: 签收留痕 | D69: 法·管 | E69: 《劳动合同法》第4条 | F69: 员工手册/制度经员工签收确认 | G69: 未签收无法证明已告知 | H69: 员工手册发了吗？有签收吗？ | J69: ★★★★☆ | L69: P | M69: 签收表 + 归档 | N69: L2 证据能力 | O69: 一期·证据 | P69: ★★★同上 | Q69: =LEN(J69)-LEN(SUBSTITUTE(J69,"★","")) -> 4
A70: 61 | B70: ④规章制度管控 | C70: 严重违纪标准 | D70: 法 | E70: 《劳动合同法》第39条 | F70: 明确「严重违纪」具体情形与量化标准 | G70: 违纪标准模糊，据此解除被认定违法 | H70: 严重违纪怎么界定？有具体标准吗？ | J70: ★★★★★ | L70: T | M70: 奖惩管理办法 | N70: L2 证据能力 | O70: 一期·证据 | P70: ★★★「辞得了人」的基础 | Q70: =LEN(J70)-LEN(SUBSTITUTE(J70,"★","")) -> 5
A71: 62 | B71: ④规章制度管控 | C71: 罚款条款合法 | D71: 法 | E71: 《劳动法》；《工资支付暂行规定》 | F71: 企业无罚款权，不得克扣工资 | G71: 设罚款、押金、扣证件等违法内容 | H71: 制度里有罚款吗？怎么执行的？ | J71: ★★★★☆ | L71: T | M71: 绩效/奖金机制替代罚款 | N71: L2 证据能力 | O71: 一期·证据 | Q71: =LEN(J71)-LEN(SUBSTITUTE(J71,"★","")) -> 4
A72: 63 | B72: ④规章制度管控 | C72: 制度合法性 | D72: 法 | E72: 《劳动合同法》第26/80条 | F72: 制度内容不得违法，不得「就低不就高」 | G72: 制度与法律/合同冲突，条款无效 | H72: 制度内容与合同、法律有冲突吗？ | J72: ★★★☆☆ | L72: T | M72: 违法条款清理 | N72: L2 证据能力 | O72: 一期·证据 | Q72: =LEN(J72)-LEN(SUBSTITUTE(J72,"★","")) -> 3
A73: 64 | B73: ④规章制度管控 | C73: 制度更新 | D73: 法·管 | E73: 立法/司法动态 | F73: 制度随新法、新司法解释及时修订 | G73: 多年未更新，与新规脱节 | H73: 制度多久更新一次？最近一次什么时候？ | J73: ★★☆☆☆ | L73: P | M73: 定期修订机制 | N73: L2 证据能力 | O73: 一期·证据 | Q73: =LEN(J73)-LEN(SUBSTITUTE(J73,"★","")) -> 2
A74: 65 | B74: ④规章制度管控 | C74: 处分程序 | D74: 法·管 | E74: 《劳动合同法》 | F74: 设调查、申诉、送达等处分程序 | G74: 程序瑕疵导致处分/解除被推翻 | H74: 违纪处理有调查、通知、申诉程序吗？ | J74: ★★★☆☆ | L74: P | M74: 违纪调查报告 + 流程 | N74: L2 证据能力 | O74: 一期·证据 | Q74: =LEN(J74)-LEN(SUBSTITUTE(J74,"★","")) -> 3
A75: 66 | B75: ④规章制度管控 | C75: 解除依据时效 | D75: 法 | E75: 《劳动合同法》 | F75: 据以解除的制度须早于违纪行为、有效公示 | G75: 以事后制定/未公示条款解除，无效 | H75: 用来解除的制度条款是什么时候定的？ | J75: ★★★☆☆ | L75: P | M75: 制度时间与公示有效性核对 | N75: L2 证据能力 | O75: 一期·证据 | Q75: =LEN(J75)-LEN(SUBSTITUTE(J75,"★","")) -> 3
A76: 67 | B76: ④规章制度管控 | C76: 反职场性骚扰制度 | D76: 法·管 | E76: 《妇女权益保障法》(2023)；《民法典》第1010条 | F76: 建立预防与处置职场性骚扰的制度与投诉处理机制 | G76: 无防治机制，发生性骚扰用人单位担责、声誉受损 | H76: 是否有反性骚扰制度与投诉渠道？ | J76: ★★★☆☆ | L76: T | M76: 反性骚扰制度 | N76: L2 证据能力 | O76: 一期·证据 | Q76: =LEN(J76)-LEN(SUBSTITUTE(J76,"★","")) -> 3
A77: 68 | B77: ④规章制度管控 | C77: 专项制度配套 | D77: 管·法 | E77: 《劳动合同法》第4条 | F77: 考勤、薪酬、差旅、奖惩、保密等专项制度与员工手册配套 | G77: 只有手册无专项制度，管理依据不足 | H77: 除手册外有哪些专项制度？是否成体系？ | J77: ★★☆☆☆ | L77: T | M77: 专项制度清单 | N77: L2 证据能力 | O77: 一期·证据 | Q77: =LEN(J77)-LEN(SUBSTITUTE(J77,"★","")) -> 2
A78: 69 | B78: ④规章制度管控 | C78: 信息与数据安全制度 | D78: 法·管 | E78: 《数据安全法》《个人信息保护法》 | F78: 建立员工与客户信息、IT使用、数据外发的管理制度 | G78: 数据外泄、违规使用，合规与赔偿风险 | H78: 是否有IT与数据安全制度？数据外发如何管控？ | J78: ★★★☆☆ | L78: T | M78: 信息安全管理制度 | N78: L4 资产保护 | O78: 选配·按业务 | Q78: =LEN(J78)-LEN(SUBSTITUTE(J78,"★","")) -> 3
A79: ⑤薪酬福利管控 （15 项）
A80: 70 | B80: ⑤薪酬福利管控 | C80: 工资结构清晰 | D80: 法·税 | E80: 《关于工资总额组成的规定》 | F80: 工资构成清晰（基本/绩效/补贴），口径稳定 | G80: 结构混同，经济补偿、加班费基数被做高 | H80: 工资由哪些部分构成？怎么发的？ | J80: ★★★★☆ | L80: S | M80: 薪酬结构设计方案 | N80: L3 结构 | O80: 二期·结构 | P80: ★★★结构层核心:决定社保基数与加班费基数 | Q80: =LEN(J80)-LEN(SUBSTITUTE(J80,"★","")) -> 4
A81: 71 | B81: ⑤薪酬福利管控 | C81: 最低工资 | D81: 法 | E81: 《最低工资规定》 | F81: 实发不低于当地最低工资标准 | G81: 试用期/淡季实发低于最低工资 | H81: 是否存在实发低于最低工资的情况？ | J81: ★★★★☆ | L81: P | M81: 最低工资动态对标机制 | N81: L1 负债型 | O81: ★立即 | P81: 低于最低工资须补差 | Q81: =LEN(J81)-LEN(SUBSTITUTE(J81,"★","")) -> 4
A82: 72 | B82: ⑤薪酬福利管控 | C82: 加班费基数 | D82: 法 | E82: 《劳动法》第44条；地方规定 | F82: 加班费基数依法（部分地区不得低于约定/标准） | G82: 加班费基数偏低，集体追溯 | H82: 加班费基数怎么定的？ | J82: ★★★★☆ | L82: S | M82: 加班费基数口径方案 | N82: L1 负债型 | O82: 三期·负债 | P82: 依赖第70项 | Q82: =LEN(J82)-LEN(SUBSTITUTE(J82,"★","")) -> 4
A83: 73 | B83: ⑤薪酬福利管控 | C83: 工资支付周期 | D83: 法 | E83: 《工资支付暂行规定》 | F83: 工资按月、按约定日期足额支付 | G83: 支付周期超月、发薪日不固定 | H83: 工资多久发一次？发薪日固定吗？ | J83: ★★★☆☆ | L83: P | M83: 按月足额发薪规范 | N83: L1 负债型 | O83: ★立即 | Q83: =LEN(J83)-LEN(SUBSTITUTE(J83,"★","")) -> 3
A84: 74 | B84: ⑤薪酬福利管控 | C84: 克扣与拖欠 | D84: 法 | E84: 《劳动合同法》第38条；《保障农民工工资支付条例》 | F84: 不得克扣、无故拖欠工资 | G84: 拖欠/克扣→被迫解除+经济补偿+监察处罚 | H84: 有无拖欠、克扣、扣款情况？ | J84: ★★★★★ | L84: P | M84: 薪资台账 + 扣款规范 | N84: L1 负债型 | O84: ★立即 | Q84: =LEN(J84)-LEN(SUBSTITUTE(J84,"★","")) -> 5
A85: 75 | B85: ⑤薪酬福利管控 | C85: 绩效扣减依据 | D85: 法·管 | E85: 《工资支付暂行规定》 | F85: 绩效考核与扣减须有制度依据并公示 | G85: 绩效扣款无依据被认定克扣 | H85: 绩效扣款有制度依据吗？公示了吗？ | J85: ★★★☆☆ | L85: T | M85: 绩效制度 | N85: L2 证据能力 | O85: 一期·证据 | Q85: =LEN(J85)-LEN(SUBSTITUTE(J85,"★","")) -> 3
A86: 76 | B86: ⑤薪酬福利管控 | C86: 工资条 | D86: 法·管 | E86: 《工资支付暂行规定》 | F86: 提供工资条，明细透明 | G86: 工资条不透明，员工主张差额举证有利 | H86: 提供工资条吗？明细清楚吗？ | J86: ★★☆☆☆ | L86: P | M86: 按月工资条 + 留痕 | N86: L2 证据能力 | O86: 一期·证据 | P86: 证据价值高、成本极低 | Q86: =LEN(J86)-LEN(SUBSTITUTE(J86,"★","")) -> 2
A87: 77 | B87: ⑤薪酬福利管控 | C87: 现金/私卡/阴阳工资 | D87: 法·税 | E87: 《个人所得税法》；金税四期 | F87: 工资对公代发、据实申报 | G87: 现金/私卡/阴阳工资逃税，留痕暴露 | H87: 工资怎么发？是否有现金或私卡发薪？ | J87: ★★★★★ | L87: S | M87: 对公代发重构方案 | N87: L1 负债型 | O87: ★立即 | P87: ★税务负债每月在长;须先解 L3 薪酬结构 | Q87: =LEN(J87)-LEN(SUBSTITUTE(J87,"★","")) -> 5
A88: 78 | B88: ⑤薪酬福利管控 | C88: 年终奖与提成 | D88: 法·业 | E88: 《劳动合同法》；司法实践 | F88: 年终奖/提成发放条件书面明确 | G88: 条件不明、离职不发引发争议 | H88: 年终奖、提成怎么约定的？离职发吗？ | J88: ★★★☆☆ | L88: T | M88: 提成/奖金方案(含离职处理) | N88: L2 证据能力 | O88: 一期·证据 | Q88: =LEN(J88)-LEN(SUBSTITUTE(J88,"★","")) -> 3
A89: 79 | B89: ⑤薪酬福利管控 | C89: 计件单价 | D89: 法·业 | E89: 《劳动法》 | F89: 计件单价书面约定，不得随意下调 | G89: 计件单价单方下调，引发争议 | H89: 计件单价怎么定的？会调整吗？ | J89: ★★★☆☆ | L89: T | M89: 计件单价规则 | N89: L2 证据能力 | O89: 一期·证据 | Q89: =LEN(J89)-LEN(SUBSTITUTE(J89,"★","")) -> 3
A90: 80 | B90: ⑤薪酬福利管控 | C90: 补偿基数计算 | D90: 法·人 | E90: 《劳动合同法》第47条 | F90: 经济补偿/代通知金基数按法定口径 | G90: N、N+1、2N基数算错，超付或被诉 | H90: 离职补偿怎么算的？基数取什么？ | J90: ★★★☆☆ | L90: T | M90: 补偿计算表 | N90: L2 证据能力 | O90: 一期·证据 | Q90: =LEN(J90)-LEN(SUBSTITUTE(J90,"★","")) -> 3
A91: 81 | B91: ⑤薪酬福利管控 | C91: 试用期工资合规 | D91: 法·人 | E91: 《劳动合同法》第20条 | F91: 试用期工资≥本单位同岗最低档/合同工资80%，且≥最低工资 | G91: 试用期工资过低，补差额并被监察处罚 | H91: 试用期工资怎么定？是否达80%且不低于最低工资？ | J91: ★★★☆☆ | L91: T | M91: 试用期工资标准 | N91: L1 负债型 | O91: 三期·负债 | Q91: =LEN(J91)-LEN(SUBSTITUTE(J91,"★","")) -> 3
A92: 82 | B92: ⑤薪酬福利管控 | C92: 待岗停工工资 | D92: 法·管 | E92: 《工资支付暂行规定》第12条；地方规定 | F92: 停工停产首个周期付工资，之后付生活费(不低于当地标准) | G92: 待岗期间不付/乱付工资，被迫解除+补偿 | H92: 有无待岗/停工情形？期间如何发放工资生活费？ | J92: ★★★☆☆ | L92: T | M92: 待岗管理办法 | N92: L0 事件型 | O92: 备用·用到再补 | Q92: =LEN(J92)-LEN(SUBSTITUTE(J92,"★","")) -> 3
A93: 83 | B93: ⑤薪酬福利管控 | C93: 工资支付记录保存 | D93: 法·管 | E93: 《工资支付暂行规定》第6条 | F93: 工资支付记录至少保存2年备查 | G93: 记录缺失，争议中举证不利 | H93: 工资表、工资条记录保存多久？能否调取？ | J93: ★★☆☆☆ | L93: P | M93: 工资台账 + 归档 | N93: L2 证据能力 | O93: 一期·证据 | P93: ★举证关键 | Q93: =LEN(J93)-LEN(SUBSTITUTE(J93,"★","")) -> 2
A94: 84 | B94: ⑤薪酬福利管控 | C94: 法定津贴福利合规 | D94: 法·业 | E94: 《防暑降温措施管理办法》等 | F94: 高温津贴、特殊岗位津贴等依规发放并合规计税 | G94: 漏发高温津贴等被投诉、补发 | H94: 是否有高温/特殊津贴？是否依规发放？ | J94: ★★☆☆☆ | L94: T | M94: 津贴发放标准 | N94: L2 证据能力 | O94: 一期·证据 | P94: 关联社保基数排除项设计 | Q94: =LEN(J94)-LEN(SUBSTITUTE(J94,"★","")) -> 2
A95: ⑥社保公积金管控 （13 项）
A96: 85 | B96: ⑥社保公积金管控 | C96: 应保尽保（入职即保） | D96: 法·税 | E96: 《社会保险法》第57/58条 | F96: 用工之日起30日内办理社保参保登记 | G96: 未参保/迟保→补缴+滞纳金+工伤全担 | H96: 入职多久交社保？有无未参保人员？ | J96: ★★★★★ | L96: P | M96: 参保登记表 + 即保流程 | N96: L1 负债型 | O96: ★立即 | P96: 存量未保→转 S 方案 | Q96: =LEN(J96)-LEN(SUBSTITUTE(J96,"★","")) -> 5
A97: 86 | B97: ⑥社保公积金管控 | C97: 放弃社保无效 | D97: 法 | E97: 法释〔2025〕12号第十九条 | F97: 「自愿放弃社保」约定一律无效 | G97: 凭放弃书未缴，仍被迫解除+补缴 | H97: 有无员工签过放弃社保承诺？ | J97: ★★★★★ | L97: S | M97: 放弃承诺清理 + 员工沟通方案 | N97: L1 负债型 | O97: ★立即 | P97: ★需配套员工沟通,防引爆 | Q97: =LEN(J97)-LEN(SUBSTITUTE(J97,"★","")) -> 5
A98: 87 | B98: ⑥社保公积金管控 | C98: 缴费基数足额 | D98: 法·税 | E98: 《社会保险法》第60-63条 | F98: 按上年度月平均工资核定缴费基数 | G98: 按最低基数缴→补差额+滞纳金 | H98: 社保基数怎么定的？是否按最低基数？ | J98: ★★★★☆ | L98: S | M98: 基数测算 + 三年过渡方案 | N98: L1 负债型 | O98: 三期·负债 | P98: ★★★合规线王牌产品 | Q98: =LEN(J98)-LEN(SUBSTITUTE(J98,"★","")) -> 4
A99: 88 | B99: ⑥社保公积金管控 | C99: 三表一致 | D99: 税·法 | E99: 金税四期；《个人所得税法》 | F99: 工资表/个税/社保基数口径一致 | G99: 三表不符触发预警、全员历史追溯 | H99: 工资、个税、社保数据一致吗？ | J99: ★★★★★ | L99: S | M99: 三表口径统一方案 | N99: L1 负债型 | O99: 三期·负债 | Q99: =LEN(J99)-LEN(SUBSTITUTE(J99,"★","")) -> 5
A100: 89 | B100: ⑥社保公积金管控 | C100: 试用期参保 | D100: 法 | E100: 《社会保险法》 | F100: 试用期同样应依法参保 | G100: 「转正后再缴」违法 | H100: 试用期交社保吗？ | J100: ★★★★☆ | L100: P | M100: 试用期即参保 | N100: L1 负债型 | O100: ★立即 | Q100: =LEN(J100)-LEN(SUBSTITUTE(J100,"★","")) -> 4
A101: 90 | B101: ⑥社保公积金管控 | C101: 补贴换社保 | D101: 法·税 | E101: 《社会保险法》 | F101: 不得以现金补贴替代社保缴纳 | G101: 补贴换社保约定无效，仍须补缴 | H101: 有无以补贴替代社保的安排？ | J101: ★★★★☆ | L101: S | M101: 补贴换保清理方案 | N101: L1 负债型 | O101: 三期·负债 | Q101: =LEN(J101)-LEN(SUBSTITUTE(J101,"★","")) -> 4
...

Sheet 税务维度专项诊断
A1: 税务维度专项诊断 V2 —— 金税四期 · 社保入税 · 三表一致
A2: 12 项。同样带分流四列。★ 与主表部分项目同源(#77/#87/#88/#35),在备注中已标明 —— 生成交付清单时须去重。
A4: 序号 | B4: 诊断项 | C4: 法规/政策依据 | D4: 合规要求(应然) | E4: 常见风险 | F4: 核查要点 | G4: 现状记录 | H4: 风险判定 | I4: 【风控】分流 | J4: 【风控】交付物 | K4: 【合规】层级 | L4: 【合规】建议期次 | M4: 备注/提示
A5: 1 | B5: 三表一致 | C5: 金税四期；《个人所得税法》；《社会保险法》 | D5: 工资表、个税申报、社保缴费基数三处口径一致 | E5: 三表不符触发预警，全员历史数据被追溯 | F5: 调取工资表、个税申报表、社保缴费明细比对 | I5: S | J5: 三表口径统一方案 | K5: L1 负债型 | L5: 三期·负债 | M5: 与主表 #88 同源
A6: 2 | B6: 社保基数据实 | C6: 《社会保险法》第60-63条 | D6: 按上年度月平均工资足额核定社保基数 | E6: 按最低基数缴纳→补差额+滞纳金 | F6: 抽查基数与实发工资是否匹配 | I6: S | J6: 基数测算 + 三年过渡方案 | K6: L1 负债型 | L6: 三期·负债 | M6: 与主表 #87 同源
A7: 3 | B7: 对公代发工资 | C7: 《个人所得税法》；金税四期 | D7: 工资通过对公账户代发并据实申报个税 | E7: 现金/私人卡发薪逃避个税，留痕暴露 | F7: 核查发薪渠道与银行流水 | I7: S | J7: 对公代发重构方案 | K7: L1 负债型 | L7: ★立即 | M7: 与主表 #77 同源
A8: 4 | B8: 阴阳工资/两套账 | C8: 《个人所得税法》；《税收征收管理法》 | D8: 工资据实申报，禁止阴阳工资与两套账 | E8: 少报工资逃税→补税+罚款+滞纳金 | F8: 比对申报工资与实发工资 | I8: S | J8: 两套账清理 + 据实申报方案 | K8: L1 负债型 | L8: ★立即 | M8: ★税务负债每月在长
A9: 5 | B9: 劳务报酬代扣代缴 | C9: 《个人所得税法》第8/9条 | D9: 对兼职、外部人员劳务报酬依法代扣代缴个税 | E9: 未代扣代缴，企业被追责并加收滞纳金 | F9: 核查劳务人员报酬的个税处理 | I9: P | J9: 劳务报酬代扣机制 + 台账 | K9: L1 负债型 | L9: ★立即 | M9: 未代扣代缴,企业被追责并加滞纳金
A10: 6 | B10: 灵活用工/委托代征 | C10: 平台用工与税收政策 | D10: 业务真实、合同/资金/发票/服务四流一致 | E10: 假业务虚开发票，行政乃至刑事风险 | F10: 核查灵活用工业务真实性与发票 | I10: S | J10: 灵活用工合规设计(四流一致) | K10: L3 结构 | L10: 二期·结构 | M10: 与主表 #35 同源;虚开有刑事风险
A11: 7 | B11: 个税专项附加扣除 | C11: 《个人所得税法》 | D11: 收集并留存员工专项附加扣除资料 | E11: 资料缺失被纳税调整 | F11: 抽查专项附加扣除资料留存 | I11: P | J11: 专项附加扣除资料留存规范 | K11: L0 事件型 | L11: 备用·用到再补
A12: 8 | B12: 补贴/福利个税 | C12: 《个人所得税法》 | D12: 各类补贴福利依规并入计税或合规免税 | E12: 高温/通讯/餐补等未并入计税或未代扣 | F12: 核查补贴福利的个税处理 | I12: T | J12: 补贴福利计税口径表 | K12: L2 证据能力 | L12: 一期·证据 | M12: ★关联社保基数排除项设计(防暑降温费等)
A13: 9 | B13: 年终奖计税 | C13: 个税年终奖计税政策 | D13: 合理选择单独/合并计税方式 | E13: 计税方式错误，多缴或漏缴 | F13: 核查年终奖计税方式 | I13: T | J13: 年终奖计税方式选择 | K13: L0 事件型 | L13: 备用·用到再补
A14: 10 | B14: 残保金 | C14: 残疾人就业保障金政策 | D14: 按比例安排残疾人就业或缴纳残保金 | E14: 漏缴/少缴残保金被追缴 | F14: 核查残疾人安排与残保金缴纳 | I14: P | J14: 残保金核算与安排 | K14: L1 负债型 | L14: 三期·负债 | M14: 漏缴被追缴
A15: 11 | B15: 工会经费 | C15: 《工会法》 | D15: 按工资总额2%计提工会经费 | E15: 漏计提工会经费 | F15: 核查工会经费计提 | I15: P | J15: 工会经费计提规范 | K15: L1 负债型 | L15: 三期·负债 | M15: 按工资总额2%计提
A16: 12 | B16: 社保入税征管 | C16: 社保入税征管政策 | D16: 税务统一征收，历史欠缴可被追征 | E16: 历史欠缴在稽核中暴露被追征 | F16: 评估历史欠缴敞口 | I16: S | J16: 历史敞口测算 + 化解方案 | K16: L1 负债型 | L16: 三期·负债 | M16: ★社保入税:历史欠缴可被追征

Sheet 风险汇总与应对方案
A1: 风险汇总与应对方案
A2: ★ 已改为公式联动 —— 主表 K 列判定一填,此表自动跳数,不再手工统计。
A4: 板块 | B4: 高风险 | C4: 中风险 | D4: 低风险 | E4: 合规 | F4: 待核实 | G4: 固有高风险项(★≥4) | H4: 应对优先级 | I4: 责任人 | J4: 计划完成时间 | K4: 备注
A5: ①招聘入职管控 | B5: =COUNTIFS(十大板块诊断主表!$B$5:$B$166,$A5,十大板块诊断主表!$K$5:$K$166,"高风险") -> 0 | C5: =COUNTIFS(十大板块诊断主表!$B$5:$B$166,$A5,十大板块诊断主表!$K$5:$K$166,"中风险") -> 0 | D5: =COUNTIFS(十大板块诊断主表!$B$5:$B$166,$A5,十大板块诊断主表!$K$5:$K$166,"低风险") -> 0 | E5: =COUNTIFS(十大板块诊断主表!$B$5:$B$166,$A5,十大板块诊断主表!$K$5:$K$166,"合规") -> 0 | F5: =COUNTIFS(十大板块诊断主表!$B$5:$B$166,$A5,十大板块诊断主表!$K$5:$K$166,"待核实") -> 0 | G5: =COUNTIFS(十大板块诊断主表!$B$5:$B$166,$A5,十大板块诊断主表!$Q$5:$Q$166,">=4") -> 6 | H5: =IF(B5>0,"① 高",IF(C5>0,"② 中",IF(F5>0,"③ 待核实",IF(D5>0,"④ 低","⑤ 合规")))) -> ⑤ 合规
A6: ②劳动关系管控 | B6: =COUNTIFS(十大板块诊断主表!$B$5:$B$166,$A6,十大板块诊断主表!$K$5:$K$166,"高风险") -> 0 | C6: =COUNTIFS(十大板块诊断主表!$B$5:$B$166,$A6,十大板块诊断主表!$K$5:$K$166,"中风险") -> 0 | D6: =COUNTIFS(十大板块诊断主表!$B$5:$B$166,$A6,十大板块诊断主表!$K$5:$K$166,"低风险") -> 0 | E6: =COUNTIFS(十大板块诊断主表!$B$5:$B$166,$A6,十大板块诊断主表!$K$5:$K$166,"合规") -> 0 | F6: =COUNTIFS(十大板块诊断主表!$B$5:$B$166,$A6,十大板块诊断主表!$K$5:$K$166,"待核实") -> 0 | G6: =COUNTIFS(十大板块诊断主表!$B$5:$B$166,$A6,十大板块诊断主表!$Q$5:$Q$166,">=4") -> 15 | H6: =IF(B6>0,"① 高",IF(C6>0,"② 中",IF(F6>0,"③ 待核实",IF(D6>0,"④ 低","⑤ 合规")))) -> ⑤ 合规
A7: ③考勤休假管控 | B7: =COUNTIFS(十大板块诊断主表!$B$5:$B$166,$A7,十大板块诊断主表!$K$5:$K$166,"高风险") -> 0 | C7: =COUNTIFS(十大板块诊断主表!$B$5:$B$166,$A7,十大板块诊断主表!$K$5:$K$166,"中风险") -> 0 | D7: =COUNTIFS(十大板块诊断主表!$B$5:$B$166,$A7,十大板块诊断主表!$K$5:$K$166,"低风险") -> 0 | E7: =COUNTIFS(十大板块诊断主表!$B$5:$B$166,$A7,十大板块诊断主表!$K$5:$K$166,"合规") -> 0 | F7: =COUNTIFS(十大板块诊断主表!$B$5:$B$166,$A7,十大板块诊断主表!$K$5:$K$166,"待核实") -> 0 | G7: =COUNTIFS(十大板块诊断主表!$B$5:$B$166,$A7,十大板块诊断主表!$Q$5:$Q$166,">=4") -> 5 | H7: =IF(B7>0,"① 高",IF(C7>0,"② 中",IF(F7>0,"③ 待核实",IF(D7>0,"④ 低","⑤ 合规")))) -> ⑤ 合规
A8: ④规章制度管控 | B8: =COUNTIFS(十大板块诊断主表!$B$5:$B$166,$A8,十大板块诊断主表!$K$5:$K$166,"高风险") -> 0 | C8: =COUNTIFS(十大板块诊断主表!$B$5:$B$166,$A8,十大板块诊断主表!$K$5:$K$166,"中风险") -> 0 | D8: =COUNTIFS(十大板块诊断主表!$B$5:$B$166,$A8,十大板块诊断主表!$K$5:$K$166,"低风险") -> 0 | E8: =COUNTIFS(十大板块诊断主表!$B$5:$B$166,$A8,十大板块诊断主表!$K$5:$K$166,"合规") -> 0 | F8: =COUNTIFS(十大板块诊断主表!$B$5:$B$166,$A8,十大板块诊断主表!$K$5:$K$166,"待核实") -> 0 | G8: =COUNTIFS(十大板块诊断主表!$B$5:$B$166,$A8,十大板块诊断主表!$Q$5:$Q$166,">=4") -> 6 | H8: =IF(B8>0,"① 高",IF(C8>0,"② 中",IF(F8>0,"③ 待核实",IF(D8>0,"④ 低","⑤ 合规")))) -> ⑤ 合规
A9: ⑤薪酬福利管控 | B9: =COUNTIFS(十大板块诊断主表!$B$5:$B$166,$A9,十大板块诊断主表!$K$5:$K$166,"高风险") -> 0 | C9: =COUNTIFS(十大板块诊断主表!$B$5:$B$166,$A9,十大板块诊断主表!$K$5:$K$166,"中风险") -> 0 | D9: =COUNTIFS(十大板块诊断主表!$B$5:$B$166,$A9,十大板块诊断主表!$K$5:$K$166,"低风险") -> 0 | E9: =COUNTIFS(十大板块诊断主表!$B$5:$B$166,$A9,十大板块诊断主表!$K$5:$K$166,"合规") -> 0 | F9: =COUNTIFS(十大板块诊断主表!$B$5:$B$166,$A9,十大板块诊断主表!$K$5:$K$166,"待核实") -> 0 | G9: =COUNTIFS(十大板块诊断主表!$B$5:$B$166,$A9,十大板块诊断主表!$Q$5:$Q$166,">=4") -> 5 | H9: =IF(B9>0,"① 高",IF(C9>0,"② 中",IF(F9>0,"③ 待核实",IF(D9>0,"④ 低","⑤ 合规")))) -> ⑤ 合规
A10: ⑥社保公积金管控 | B10: =COUNTIFS(十大板块诊断主表!$B$5:$B$166,$A10,十大板块诊断主表!$K$5:$K$166,"高风险") -> 0 | C10: =COUNTIFS(十大板块诊断主表!$B$5:$B$166,$A10,十大板块诊断主表!$K$5:$K$166,"中风险") -> 0 | D10: =COUNTIFS(十大板块诊断主表!$B$5:$B$166,$A10,十大板块诊断主表!$K$5:$K$166,"低风险") -> 0 | E10: =COUNTIFS(十大板块诊断主表!$B$5:$B$166,$A10,十大板块诊断主表!$K$5:$K$166,"合规") -> 0 | F10: =COUNTIFS(十大板块诊断主表!$B$5:$B$166,$A10,十大板块诊断主表!$K$5:$K$166,"待核实") -> 0 | G10: =COUNTIFS(十大板块诊断主表!$B$5:$B$166,$A10,十大板块诊断主表!$Q$5:$Q$166,">=4") -> 8 | H10: =IF(B10>0,"① 高",IF(C10>0,"② 中",IF(F10>0,"③ 待核实",IF(D10>0,"④ 低","⑤ 合规")))) -> ⑤ 合规
A11: ⑦工伤职业病管控 | B11: =COUNTIFS(十大板块诊断主表!$B$5:$B$166,$A11,十大板块诊断主表!$K$5:$K$166,"高风险") -> 0 | C11: =COUNTIFS(十大板块诊断主表!$B$5:$B$166,$A11,十大板块诊断主表!$K$5:$K$166,"中风险") -> 0 | D11: =COUNTIFS(十大板块诊断主表!$B$5:$B$166,$A11,十大板块诊断主表!$K$5:$K$166,"低风险") -> 0 | E11: =COUNTIFS(十大板块诊断主表!$B$5:$B$166,$A11,十大板块诊断主表!$K$5:$K$166,"合规") -> 0 | F11: =COUNTIFS(十大板块诊断主表!$B$5:$B$166,$A11,十大板块诊断主表!$K$5:$K$166,"待核实") -> 0 | G11: =COUNTIFS(十大板块诊断主表!$B$5:$B$166,$A11,十大板块诊断主表!$Q$5:$Q$166,">=4") -> 6 | H11: =IF(B11>0,"① 高",IF(C11>0,"② 中",IF(F11>0,"③ 待核实",IF(D11>0,"④ 低","⑤ 合规")))) -> ⑤ 合规
A12: ⑧离职管控 | B12: =COUNTIFS(十大板块诊断主表!$B$5:$B$166,$A12,十大板块诊断主表!$K$5:$K$166,"高风险") -> 0 | C12: =COUNTIFS(十大板块诊断主表!$B$5:$B$166,$A12,十大板块诊断主表!$K$5:$K$166,"中风险") -> 0 | D12: =COUNTIFS(十大板块诊断主表!$B$5:$B$166,$A12,十大板块诊断主表!$K$5:$K$166,"低风险") -> 0 | E12: =COUNTIFS(十大板块诊断主表!$B$5:$B$166,$A12,十大板块诊断主表!$K$5:$K$166,"合规") -> 0 | F12: =COUNTIFS(十大板块诊断主表!$B$5:$B$166,$A12,十大板块诊断主表!$K$5:$K$166,"待核实") -> 0 | G12: =COUNTIFS(十大板块诊断主表!$B$5:$B$166,$A12,十大板块诊断主表!$Q$5:$Q$166,">=4") -> 10 | H12: =IF(B12>0,"① 高",IF(C12>0,"② 中",IF(F12>0,"③ 待核实",IF(D12>0,"④ 低","⑤ 合规")))) -> ⑤ 合规
A13: ⑨员工关系管控 | B13: =COUNTIFS(十大板块诊断主表!$B$5:$B$166,$A13,十大板块诊断主表!$K$5:$K$166,"高风险") -> 0 | C13: =COUNTIFS(十大板块诊断主表!$B$5:$B$166,$A13,十大板块诊断主表!$K$5:$K$166,"中风险") -> 0 | D13: =COUNTIFS(十大板块诊断主表!$B$5:$B$166,$A13,十大板块诊断主表!$K$5:$K$166,"低风险") -> 0 | E13: =COUNTIFS(十大板块诊断主表!$B$5:$B$166,$A13,十大板块诊断主表!$K$5:$K$166,"合规") -> 0 | F13: =COUNTIFS(十大板块诊断主表!$B$5:$B$166,$A13,十大板块诊断主表!$K$5:$K$166,"待核实") -> 0 | G13: =COUNTIFS(十大板块诊断主表!$B$5:$B$166,$A13,十大板块诊断主表!$Q$5:$Q$166,">=4") -> 1 | H13: =IF(B13>0,"① 高",IF(C13>0,"② 中",IF(F13>0,"③ 待核实",IF(D13>0,"④ 低","⑤ 合规")))) -> ⑤ 合规
A14: ⑩劳动争议管控 | B14: =COUNTIFS(十大板块诊断主表!$B$5:$B$166,$A14,十大板块诊断主表!$K$5:$K$166,"高风险") -> 0 | C14: =COUNTIFS(十大板块诊断主表!$B$5:$B$166,$A14,十大板块诊断主表!$K$5:$K$166,"中风险") -> 0 | D14: =COUNTIFS(十大板块诊断主表!$B$5:$B$166,$A14,十大板块诊断主表!$K$5:$K$166,"低风险") -> 0 | E14: =COUNTIFS(十大板块诊断主表!$B$5:$B$166,$A14,十大板块诊断主表!$K$5:$K$166,"合规") -> 0 | F14: =COUNTIFS(十大板块诊断主表!$B$5:$B$166,$A14,十大板块诊断主表!$K$5:$K$166,"待核实") -> 0 | G14: =COUNTIFS(十大板块诊断主表!$B$5:$B$166,$A14,十大板块诊断主表!$Q$5:$Q$166,">=4") -> 2 | H14: =IF(B14>0,"① 高",IF(C14>0,"② 中",IF(F14>0,"③ 待核实",IF(D14>0,"④ 低","⑤ 合规")))) -> ⑤ 合规
A15: 合计 | B15: =SUM(B5:B14) -> 0 | C15: =SUM(C5:C14) -> 0 | D15: =SUM(D5:D14) -> 0 | E15: =SUM(E5:E14) -> 0 | F15: =SUM(F5:F14) -> 0 | G15: =SUM(G5:G14) -> 64
A17: ★ 优先级读法:① 高 = 有高风险项,须优先;⑤ 合规 = 该板块无问题。 ★「固有高风险项(★≥4)」是该板块本身的固有雷区数量,与本次判定无关 —— 即使本次判定为合规,这些项仍须持续管控。 ★ 责任人 / 完成时间 / 备注 三列为手填,用于整改跟踪与陪跑。

Sheet 交付清单汇总
A1: 交付清单汇总 —— 诊断完,交付量当场可见
A2: 只统计判定为「高风险 / 中风险 / 待核实」的项(判定为合规 / 低风险的不进交付)。可直接用于报价与工作量估算。
A4: 一、按分流类型(决定交付形态与收费方式)
A5: 分流类型 | B5: 需交付项数 | C5: 占比 | D5: 含义 / 交付形态与收费
A6: T | B6: =SUMPRODUCT((十大板块诊断主表!$L$5:$L$166="T")*((十大板块诊断主表!$K$5:$K$166="高风险")+(十大板块诊断主表!$K$5:$K$166="中风险")+(十大板块诊断主表!$K$5:$K$166="待核实"))) -> 0 | C6: =IF($B$9=0,"",B6/$B$9) | D6: 文本型 —— 从模板库挑、填变量即可。零边际成本。含在方案定制费内
A7: P | B7: =SUMPRODUCT((十大板块诊断主表!$L$5:$L$166="P")*((十大板块诊断主表!$K$5:$K$166="高风险")+(十大板块诊断主表!$K$5:$K$166="中风险")+(十大板块诊断主表!$K$5:$K$166="待核实"))) -> 0 | C7: =IF($B$9=0,"",B7/$B$9) | D7: 流程型 —— SOP+台账+培训,须有人带着落地。★「落地指导 / 陪跑」的收费依据
A8: S | B8: =SUMPRODUCT((十大板块诊断主表!$L$5:$L$166="S")*((十大板块诊断主表!$K$5:$K$166="高风险")+(十大板块诊断主表!$K$5:$K$166="中风险")+(十大板块诊断主表!$K$5:$K$166="待核实"))) -> 0 | C8: =IF($B$9=0,"",B8/$B$9) | D8: 方案型 —— 一事一议定制,须另填《个案信息表》。★ 高价交付,按项目 / 按事件收费
A9: 合计 | B9: =SUM(B6:B8) -> 0
A11: 二、按建议期次(决定分期方案与报价结构)
A12: 建议期次 | B12: 需交付项数 | C12: 占比 | D12: 说明
A13: ★立即 | B13: =SUMPRODUCT((十大板块诊断主表!$O$5:$O$166="★立即")*((十大板块诊断主表!$K$5:$K$166="高风险")+(十大板块诊断主表!$K$5:$K$166="中风险")+(十大板块诊断主表!$K$5:$K$166="待核实"))) -> 0 | C13: =IF($B$20=0,"",B13/$B$20) | D13: 不能等。诊断当天必须跟老板讲 —— 这是你的「必讲清单」
A14: 一期·证据 | B14: =SUMPRODUCT((十大板块诊断主表!$O$5:$O$166="一期·证据")*((十大板块诊断主表!$K$5:$K$166="高风险")+(十大板块诊断主表!$K$5:$K$166="中风险")+(十大板块诊断主表!$K$5:$K$166="待核实"))) -> 0 | C14: =IF($B$20=0,"",B14/$B$20) | D14: 制度合法、民主程序、留痕。★ 几乎不增加用工成本,做完拿回管理权。信任起手式
A15: 二期·结构 | B15: =SUMPRODUCT((十大板块诊断主表!$O$5:$O$166="二期·结构")*((十大板块诊断主表!$K$5:$K$166="高风险")+(十大板块诊断主表!$K$5:$K$166="中风险")+(十大板块诊断主表!$K$5:$K$166="待核实"))) -> 0 | C15: =IF($B$20=0,"",B15/$B$20) | D15: 主体、用工形式、薪酬结构。底座 —— 逻辑上最先想,动手可放第二期
A16: 三期·负债 | B16: =SUMPRODUCT((十大板块诊断主表!$O$5:$O$166="三期·负债")*((十大板块诊断主表!$K$5:$K$166="高风险")+(十大板块诊断主表!$K$5:$K$166="中风险")+(十大板块诊断主表!$K$5:$K$166="待核实"))) -> 0 | C16: =IF($B$20=0,"",B16/$B$20) | D16: 社保基数、加班费、工时。★ 最贵,分 2–3 年,用工具对冲
A17: 选配·按业务 | B17: =SUMPRODUCT((十大板块诊断主表!$O$5:$O$166="选配·按业务")*((十大板块诊断主表!$K$5:$K$166="高风险")+(十大板块诊断主表!$K$5:$K$166="中风险")+(十大板块诊断主表!$K$5:$K$166="待核实"))) -> 0 | C17: =IF($B$20=0,"",B17/$B$20) | D17: 商密、竞业、IP、高管。技术 / 销售型必做,其他可缓
A18: 备用·用到再补 | B18: =SUMPRODUCT((十大板块诊断主表!$O$5:$O$166="备用·用到再补")*((十大板块诊断主表!$K$5:$K$166="高风险")+(十大板块诊断主表!$K$5:$K$166="中风险")+(十大板块诊断主表!$K$5:$K$166="待核实"))) -> 0 | C18: =IF($B$20=0,"",B18/$B$20) | D18: 事件型,平时零负债。★ 明确告诉客户「这些不用管」
A19: 风控线·个案 | B19: =SUMPRODUCT((十大板块诊断主表!$O$5:$O$166="风控线·个案")*((十大板块诊断主表!$K$5:$K$166="高风险")+(十大板块诊断主表!$K$5:$K$166="中风险")+(十大板块诊断主表!$K$5:$K$166="待核实"))) -> 0 | C19: =IF($B$20=0,"",B19/$B$20) | D19: 裁员、工伤和解、仲裁应诉。走风控线,按项目 / 按事件收费
A20: 合计 | B20: =SUM(B13:B19) -> 0
